spond_classes/__init__.py
spond_classes/event.py
spond_classes/group.py
spond_classes/member.py
spond_classes/profile_.py
spond_classes/py.typed
spond_classes/role.py
spond_classes/subgroup.py
spond_classes/typing.py
spond_classes-0.17.0.dist-info/METADATA
spond_classes-0.17.0.dist-info/WHEEL
spond_classes-0.17.0.dist-info/licenses/LICENSE
spond_classes-0.17.0.dist-info/RECORD
