Metadata-Version: 2.4
Name: spond-classes
Version: 0.17.0
Summary: Unofficial class abstraction layer for the `spond` library package.
License: GPL-3.0-only
License-File: LICENSE
Author: elliot-100
Author-email: 3186037+elliot-100@users.noreply.github.com
Requires-Python: >=3.10,<4
Classifier: License :: OSI Approved :: GNU General Public License v3 (GPLv3)
Classifier: Programming Language :: Python :: 3
Classifier: Programming Language :: Python :: 3.10
Classifier: Programming Language :: Python :: 3.11
Classifier: Programming Language :: Python :: 3.12
Classifier: Programming Language :: Python :: 3.13
Classifier: Programming Language :: Python :: 3.14
Requires-Dist: pydantic[email] (>=2.7.1)
Project-URL: Documentation, https://elliot-100.github.io/Spond-classes/
Project-URL: Repository, https://github.com/elliot-100/Spond-classes
